[
  {
    "productId": "4571609335016",
    "stars": 5,
    "comment": "Super cute! The quality is just as I expected."
  },
  {
    "productId": "4571609335016",
    "stars": 4,
    "comment": "The material is soft and I really like it. It would be perfect if it were a bit bigger."
  },
  {
    "productId": "4571609335245",
    "stars": 3,
    "comment": "Pretty cute, but a little pricey."
  },
  {
    "productId": "4571609335252",
    "stars": 5,
    "comment": "So fluffy and comforting! Glad I bought it."
  },
  {
    "productId": "000000000461",
    "stars": 4,
    "comment": "Perfect cushion for outings."
  }
]
